{"info":{"subdir":"osx-arm64"},"packages":{},"packages.conda":{"cx_freeze-8.6.0.dev.1769483151-py310hfab0be0_0.conda":{"build":"py310hfab0be0_0","build_number":0,"depends":["dmgbuild >=1.6.1","freeze-core >=0.4.0","packaging >=24.0","python >=3.10,<3.11.0a0","python_abi 3.10.* *_cp310","setuptools >=78.1.1","tomli >=2.0.1"],"legacy_bz2_md5":null,"license":"PSF-2.0","license_family":"PSF","md5":"3708f6533601bb74b3d54a8b67858b22","name":"cx_freeze","sha256":"074d0318d13364b496bee3f0b7ec3ba07d3af948ef76ca6cf94235f95f74f818","size":1416116,"subdir":"osx-arm64","timestamp":1770454669469,"version":"8.6.0.dev.1769483151"},"cx_freeze-8.6.0.dev.1769483151-py311hb08d9a6_0.conda":{"build":"py311hb08d9a6_0","build_number":0,"depends":["dmgbuild >=1.6.1","freeze-core >=0.4.0","packaging >=24.0","python >=3.11,<3.12.0a0","python_abi 3.11.* *_cp311","setuptools >=78.1.1"],"legacy_bz2_md5":null,"license":"PSF-2.0","license_family":"PSF","md5":"ffc4b48b486fbde7e1475314f8ed4913","name":"cx_freeze","sha256":"9a5d550a8b10c497ed7e6aca8e4645407ba63d86669ae8cc80e6c1382131cf8d","size":1487004,"subdir":"osx-arm64","timestamp":1770454650866,"version":"8.6.0.dev.1769483151"},"cx_freeze-8.6.0.dev.1769483151-py312h92965dd_0.conda":{"build":"py312h92965dd_0","build_number":0,"depends":["dmgbuild >=1.6.1","freeze-core >=0.4.0","packaging >=24.0","python >=3.12,<3.13.0a0","python_abi 3.12.* *_cp312","setuptools >=78.1.1"],"legacy_bz2_md5":null,"license":"PSF-2.0","license_family":"PSF","md5":"caddbc687eaa08c23c4ed394f9b1e71a","name":"cx_freeze","sha256":"6721062c65e7b41726c3ba6205ae156da54f62e8da9ee05f03ec485eb7e6d0bb","size":1478333,"subdir":"osx-arm64","timestamp":1770454719252,"version":"8.6.0.dev.1769483151"},"cx_freeze-8.6.0.dev.1769483151-py313h535021f_0.conda":{"build":"py313h535021f_0","build_number":0,"depends":["dmgbuild >=1.6.1","freeze-core >=0.4.0","packaging >=24.0","python >=3.13,<3.14.0a0","python_abi 3.13.* *_cp313","setuptools >=78.1.1"],"legacy_bz2_md5":null,"license":"PSF-2.0","license_family":"PSF","md5":"dce64b2df6f38f307d08e9ce3f419c99","name":"cx_freeze","sha256":"4088fe42d661acca66699fb891fa17a4b0b5c8ecc252e52aa9502be81ee99f16","size":1482270,"subdir":"osx-arm64","timestamp":1770455247060,"version":"8.6.0.dev.1769483151"}},"removed":[],"repodata_version":1}