{"info":{"subdir":"osx-arm64"},"packages":{},"packages.conda":{"cx_freeze-8.6.0.dev.1768449333-py310hfab0be0_0.conda":{"build":"py310hfab0be0_0","build_number":0,"depends":["dmgbuild >=1.6.1","freeze-core >=0.4.0","packaging >=24.0","python >=3.10,<3.11.0a0","python_abi 3.10.* *_cp310","setuptools >=78.1.1","tomli >=2.0.1"],"license":"PSF-2.0","license_family":"PSF","md5":"a3cd08e98b98f3264113d1159757002a","name":"cx_freeze","sha256":"20395222794fa404dfcf91281df0ac5e6334a52f4ac5f875277891b8e3e49865","size":1415177,"subdir":"osx-arm64","timestamp":1768467338859,"version":"8.6.0.dev.1768449333"},"cx_freeze-8.6.0.dev.1768449333-py311hb08d9a6_0.conda":{"build":"py311hb08d9a6_0","build_number":0,"depends":["dmgbuild >=1.6.1","freeze-core >=0.4.0","packaging >=24.0","python >=3.11,<3.12.0a0","python_abi 3.11.* *_cp311","setuptools >=78.1.1"],"license":"PSF-2.0","license_family":"PSF","md5":"e58128ccd0eb0f900f6147f1c19a1493","name":"cx_freeze","sha256":"95c5314e2566e60e1105a78003adf015b5e8faf721f65a007c5c3b793c680006","size":1482144,"subdir":"osx-arm64","timestamp":1768467871453,"version":"8.6.0.dev.1768449333"},"cx_freeze-8.6.0.dev.1768449333-py312h92965dd_0.conda":{"build":"py312h92965dd_0","build_number":0,"depends":["dmgbuild >=1.6.1","freeze-core >=0.4.0","packaging >=24.0","python >=3.12,<3.13.0a0","python_abi 3.12.* *_cp312","setuptools >=78.1.1"],"license":"PSF-2.0","license_family":"PSF","md5":"bc50229c503ac1bf23d91faaec711481","name":"cx_freeze","sha256":"d6ff116b3d695e44b7ce6814f6046ba187cb9161a90268b40e9cfbc6d5399276","size":1476410,"subdir":"osx-arm64","timestamp":1768467660809,"version":"8.6.0.dev.1768449333"},"cx_freeze-8.6.0.dev.1768449333-py313h535021f_0.conda":{"build":"py313h535021f_0","build_number":0,"depends":["dmgbuild >=1.6.1","freeze-core >=0.4.0","packaging >=24.0","python >=3.13,<3.14.0a0","python_abi 3.13.* *_cp313","setuptools >=78.1.1"],"license":"PSF-2.0","license_family":"PSF","md5":"c94fbca47a845213ba7fbb304b6afdb0","name":"cx_freeze","sha256":"be64ee18caa49c5bcbda9a32268c2e470471921ff0d3be23e6f8490b798dadbc","size":1480373,"subdir":"osx-arm64","timestamp":1768467352508,"version":"8.6.0.dev.1768449333"}},"removed":[],"repodata_version":1}