{"info":{"subdir":"win-64"},"packages":{},"packages.conda":{"cx_freeze-8.4.0.dev.1747024253-py310ha8f682b_0.conda":{"build":"py310ha8f682b_0","build_number":0,"depends":["cabarchive >=0.2.4","cx_logging >=3.1","filelock >=3.12.3","packaging >=24.0","py-lief >=0.15.1","python >=3.10,<3.11.0a0","python_abi 3.10.* *_cp310","setuptools >=65.6.3","striprtf >=0.0.26","tomli >=2.0.1","ucrt >=10.0.20348.0","vc >=14.2,<15","vc14_runtime >=14.29.30139"],"legacy_bz2_md5":null,"license":"PSF-2.0","license_family":"PSF","md5":"1c337069d252b52bf02afbfc3184a17a","name":"cx_freeze","sha256":"04ebc9e24b5a0b2300ab85d9e2d174c42b497d5581284945f84ba69c9cb1bb40","size":2671916,"subdir":"win-64","timestamp":1747040444828,"version":"8.4.0.dev.1747024253"},"cx_freeze-8.4.0.dev.1747024253-py311he736701_0.conda":{"build":"py311he736701_0","build_number":0,"depends":["cabarchive >=0.2.4","cx_logging >=3.1","filelock >=3.12.3","packaging >=24.0","py-lief >=0.15.1","python >=3.11,<3.12.0a0","python_abi 3.11.* *_cp311","setuptools >=65.6.3","striprtf >=0.0.26","ucrt >=10.0.20348.0","vc >=14.2,<15","vc14_runtime >=14.29.30139"],"legacy_bz2_md5":null,"license":"PSF-2.0","license_family":"PSF","md5":"12c5a979cd09a6842ca85cfa5f4e5b39","name":"cx_freeze","sha256":"2446bb65573eac869ab7dfa228bc63385847e313d21541c5cfda46c10f9820f5","size":2757891,"subdir":"win-64","timestamp":1747040444788,"version":"8.4.0.dev.1747024253"},"cx_freeze-8.4.0.dev.1747024253-py312h4389bb4_0.conda":{"build":"py312h4389bb4_0","build_number":0,"depends":["cabarchive >=0.2.4","cx_logging >=3.1","filelock >=3.12.3","packaging >=24.0","py-lief >=0.15.1","python >=3.12,<3.13.0a0","python_abi 3.12.* *_cp312","setuptools >=65.6.3","striprtf >=0.0.26","ucrt >=10.0.20348.0","vc >=14.2,<15","vc14_runtime >=14.29.30139"],"legacy_bz2_md5":null,"license":"PSF-2.0","license_family":"PSF","md5":"65e088a03e2a16fd00e545361e651396","name":"cx_freeze","sha256":"95b97d06b70d6c2dc3bace81dd34d12074917b09c6324a35f3f9edf663cf4d30","size":2745911,"subdir":"win-64","timestamp":1747040444739,"version":"8.4.0.dev.1747024253"},"cx_freeze-8.4.0.dev.1747024253-py313ha7868ed_0.conda":{"build":"py313ha7868ed_0","build_number":0,"depends":["cabarchive >=0.2.4","cx_logging >=3.1","filelock >=3.12.3","packaging >=24.0","py-lief >=0.15.1","python >=3.13,<3.14.0a0","python_abi 3.13.* *_cp313","setuptools >=65.6.3","striprtf >=0.0.26","ucrt >=10.0.20348.0","vc >=14.2,<15","vc14_runtime >=14.29.30139"],"legacy_bz2_md5":null,"license":"PSF-2.0","license_family":"PSF","md5":"b84ed170472df534688dc10588d3d023","name":"cx_freeze","sha256":"4cdc8d26a8a8efa5dadd477b324a4aaf551ac98ec62dd8f51deb296d307cdb84","size":2745775,"subdir":"win-64","timestamp":1747040444675,"version":"8.4.0.dev.1747024253"},"cx_freeze-8.4.0.dev.1747024253-py39ha55e580_0.conda":{"build":"py39ha55e580_0","build_number":0,"depends":["cabarchive >=0.2.4","cx_logging >=3.1","filelock >=3.12.3","packaging >=24.0","py-lief >=0.15.1","python >=3.9,<3.10.0a0","python_abi 3.9.* *_cp39","setuptools >=65.6.3","striprtf >=0.0.26","tomli >=2.0.1","ucrt >=10.0.20348.0","vc >=14.2,<15","vc14_runtime >=14.29.30139"],"legacy_bz2_md5":null,"license":"PSF-2.0","license_family":"PSF","md5":"4e0a9d1e6d901b8ae872c887976ca635","name":"cx_freeze","sha256":"35e8f83ff67d269ea595b6c8e4167c8c2f5ce4ef37213b78663095152ab1dad8","size":2669462,"subdir":"win-64","timestamp":1747040444592,"version":"8.4.0.dev.1747024253"}},"removed":[],"repodata_version":1}