{"info":{"subdir":"win-64"},"packages":{},"packages.conda":{"cx_freeze-8.6.0.dev.1767433612-py310h5fa2519_0.conda":{"build":"py310h5fa2519_0","build_number":0,"depends":["cx_logging >=3.1","freeze-core >=0.4.0","packaging >=24.0","py-lief >=0.15.1","python >=3.10,<3.11.0a0","python_abi 3.10.* *_cp310","setuptools >=78.1.1","tomli >=2.0.1"],"license":"PSF-2.0","license_family":"PSF","md5":"7f16a753536ad2194c79fbc3510c00ba","name":"cx_freeze","sha256":"1e09acd726c0b3e0f334bebfadaf057213af0ca80aaa7c1130e68c5f3ecea0a3","size":1223006,"subdir":"win-64","timestamp":1767516936199,"version":"8.6.0.dev.1767433612"},"cx_freeze-8.6.0.dev.1767433612-py311h4d8bf61_0.conda":{"build":"py311h4d8bf61_0","build_number":0,"depends":["cx_logging >=3.1","freeze-core >=0.4.0","packaging >=24.0","py-lief >=0.15.1","python >=3.11,<3.12.0a0","python_abi 3.11.* *_cp311","setuptools >=78.1.1"],"license":"PSF-2.0","license_family":"PSF","md5":"87c7e067c48f6181414f1415b21f2431","name":"cx_freeze","sha256":"98e58d451a0adf5608c04e5f5e70e5f16f75b6e51ad277242b29867c8d2b0120","size":1293271,"subdir":"win-64","timestamp":1767516935607,"version":"8.6.0.dev.1767433612"},"cx_freeze-8.6.0.dev.1767433612-py312h83acffa_0.conda":{"build":"py312h83acffa_0","build_number":0,"depends":["cx_logging >=3.1","freeze-core >=0.4.0","packaging >=24.0","py-lief >=0.15.1","python >=3.12,<3.13.0a0","python_abi 3.12.* *_cp312","setuptools >=78.1.1"],"license":"PSF-2.0","license_family":"PSF","md5":"f46c539d55fad99df4ed5d2c431d3329","name":"cx_freeze","sha256":"4f8cace3c67fc974511c3a4e6f3f1ec97238a6c03f031d789253ea22c161dc88","size":1287613,"subdir":"win-64","timestamp":1767516916572,"version":"8.6.0.dev.1767433612"},"cx_freeze-8.6.0.dev.1767433612-py313hfa70ccb_0.conda":{"build":"py313hfa70ccb_0","build_number":0,"depends":["cx_logging >=3.1","freeze-core >=0.4.0","packaging >=24.0","py-lief >=0.15.1","python >=3.13,<3.14.0a0","python-msilib >=0.4.2","python_abi 3.13.* *_cp313","setuptools >=78.1.1"],"license":"PSF-2.0","license_family":"PSF","md5":"1727cbb474cb7407f38f4084b493d8b3","name":"cx_freeze","sha256":"eb2f57f4c1e48c88ae645a8e17c0b6212a1a3f8ae64d511edf56d3d1b9cad25f","size":1287314,"subdir":"win-64","timestamp":1767517002079,"version":"8.6.0.dev.1767433612"}},"removed":[],"repodata_version":1}