{"info":{"subdir":"win-64"},"packages":{},"packages.conda":{"cx_freeze-8.6.0.dev.1767018604-py310h5fa2519_0.conda":{"build":"py310h5fa2519_0","build_number":0,"depends":["cx_logging >=3.1","freeze-core >=0.4.0","packaging >=24.0","py-lief >=0.15.1","python >=3.10,<3.11.0a0","python_abi 3.10.* *_cp310","setuptools >=78.1.1","tomli >=2.0.1"],"license":"PSF-2.0","license_family":"PSF","md5":"253291cda17bd9417826dad5e6a0041d","name":"cx_freeze","sha256":"da5e0fc8c945fb82e87968ab6c44238ef8afdb9382b5c1bdee9d9830d23911fa","size":1222972,"subdir":"win-64","timestamp":1767171585856,"version":"8.6.0.dev.1767018604"},"cx_freeze-8.6.0.dev.1767018604-py311h4d8bf61_0.conda":{"build":"py311h4d8bf61_0","build_number":0,"depends":["cx_logging >=3.1","freeze-core >=0.4.0","packaging >=24.0","py-lief >=0.15.1","python >=3.11,<3.12.0a0","python_abi 3.11.* *_cp311","setuptools >=78.1.1"],"license":"PSF-2.0","license_family":"PSF","md5":"64900015a10cf188dec8679ed7aec5d1","name":"cx_freeze","sha256":"bab83de6803f4f0c7369995f31b5bb2cd254a05aef29f00e9fb49af57ad50dda","size":1293335,"subdir":"win-64","timestamp":1767171494609,"version":"8.6.0.dev.1767018604"},"cx_freeze-8.6.0.dev.1767018604-py312h83acffa_0.conda":{"build":"py312h83acffa_0","build_number":0,"depends":["cx_logging >=3.1","freeze-core >=0.4.0","packaging >=24.0","py-lief >=0.15.1","python >=3.12,<3.13.0a0","python_abi 3.12.* *_cp312","setuptools >=78.1.1"],"license":"PSF-2.0","license_family":"PSF","md5":"94f89f08d42dd080531fd10c14dad9ac","name":"cx_freeze","sha256":"d03a0d1db3317c5721873bd1e794c042ab599b40beaae335105822dc72d7a4a0","size":1286086,"subdir":"win-64","timestamp":1767171487773,"version":"8.6.0.dev.1767018604"},"cx_freeze-8.6.0.dev.1767018604-py313hfa70ccb_0.conda":{"build":"py313hfa70ccb_0","build_number":0,"depends":["cx_logging >=3.1","freeze-core >=0.4.0","packaging >=24.0","py-lief >=0.15.1","python >=3.13,<3.14.0a0","python-msilib >=0.4.2","python_abi 3.13.* *_cp313","setuptools >=78.1.1"],"license":"PSF-2.0","license_family":"PSF","md5":"2913d2194cdeab19601a8fde391830e1","name":"cx_freeze","sha256":"7e0d833f5b107b06df9e10dfeb7d914beb6a94ec5078ee6532cd7cda7da2c568","size":1287651,"subdir":"win-64","timestamp":1767171604106,"version":"8.6.0.dev.1767018604"}},"removed":[],"repodata_version":1}