{"info":{"subdir":"osx-64"},"packages":{},"packages.conda":{"cx_freeze-8.4.0.dev.1747202788-py310h69ff653_0.conda":{"build":"py310h69ff653_0","build_number":0,"depends":["__osx >=10.13","dmgbuild >=1.6.1","filelock >=3.12.3","packaging >=24.0","python >=3.10,<3.11.0a0","python >=3.10,<3.11.0a0 *_cpython","python_abi 3.10.* *_cp310","setuptools >=65.6.3","tomli >=2.0.1"],"legacy_bz2_md5":null,"license":"PSF-2.0","license_family":"PSF","md5":"bf922b808b3a109ae27e439827d7909c","name":"cx_freeze","sha256":"edb69dc70e6b7ccf13dc5f00dffaed0eb25b3c23a6855a3ba93ed9fc9dd90755","size":4127610,"subdir":"osx-64","timestamp":1747298940137,"version":"8.4.0.dev.1747202788"},"cx_freeze-8.4.0.dev.1747202788-py311hff4f217_0.conda":{"build":"py311hff4f217_0","build_number":0,"depends":["__osx >=10.13","dmgbuild >=1.6.1","filelock >=3.12.3","packaging >=24.0","python >=3.11,<3.12.0a0","python >=3.11,<3.12.0a0 *_cpython","python_abi 3.11.* *_cp311","setuptools >=65.6.3"],"legacy_bz2_md5":null,"license":"PSF-2.0","license_family":"PSF","md5":"7e3e3cc2bb47dcbacdbd22249061d65b","name":"cx_freeze","sha256":"dfb61426e176fcd7a74949e91a56c36b72212ee8e78b9e006e3d1bc7e407d512","size":4215223,"subdir":"osx-64","timestamp":1747299160952,"version":"8.4.0.dev.1747202788"},"cx_freeze-8.4.0.dev.1747202788-py312h323ca87_0.conda":{"build":"py312h323ca87_0","build_number":0,"depends":["__osx >=10.13","dmgbuild >=1.6.1","filelock >=3.12.3","packaging >=24.0","python >=3.12,<3.13.0a0","python >=3.12,<3.13.0a0 *_cpython","python_abi 3.12.* *_cp312","setuptools >=65.6.3"],"legacy_bz2_md5":null,"license":"PSF-2.0","license_family":"PSF","md5":"14ab69169e44273b4fa1b630b140768f","name":"cx_freeze","sha256":"833d9ec14fd6cb860f9d2265ab2fd2abc540b534944f66e57b1b3b507d2d3a91","size":4209678,"subdir":"osx-64","timestamp":1747298943311,"version":"8.4.0.dev.1747202788"},"cx_freeze-8.4.0.dev.1747202788-py313hb9c082b_0.conda":{"build":"py313hb9c082b_0","build_number":0,"depends":["__osx >=10.13","dmgbuild >=1.6.1","filelock >=3.12.3","packaging >=24.0","python >=3.13,<3.14.0a0","python >=3.13,<3.14.0a0 *_cp313","python_abi 3.13.* *_cp313","setuptools >=65.6.3"],"legacy_bz2_md5":null,"license":"PSF-2.0","license_family":"PSF","md5":"a3e76c25201ac9bd11d05016f7e63bfc","name":"cx_freeze","sha256":"e3edb4863fc5e0e77371cabd7b767a3286907fe4cf1a507582a8c54f3ccafe68","size":4209556,"subdir":"osx-64","timestamp":1747299337978,"version":"8.4.0.dev.1747202788"},"cx_freeze-8.4.0.dev.1747202788-py39h42342cc_0.conda":{"build":"py39h42342cc_0","build_number":0,"depends":["__osx >=10.13","dmgbuild >=1.6.1","filelock >=3.12.3","packaging >=24.0","python >=3.9,<3.10.0a0","python >=3.9,<3.10.0a0 *_cpython","python_abi 3.9.* *_cp39","setuptools >=65.6.3","tomli >=2.0.1"],"legacy_bz2_md5":null,"license":"PSF-2.0","license_family":"PSF","md5":"ef96a4a40043b5da71fa88c6460f8bf5","name":"cx_freeze","sha256":"083f1f95b24753dfdac647414838da3adf4bb21a2b9ec333a05afc054a0f8930","size":4122121,"subdir":"osx-64","timestamp":1747299261686,"version":"8.4.0.dev.1747202788"}},"removed":[],"repodata_version":1}