{"info":{"subdir":"osx-64"},"packages":{},"packages.conda":{"cx_freeze-8.1.0.dev.1744484199-py310h69ff653_0.conda":{"build":"py310h69ff653_0","build_number":0,"depends":["__osx >=10.13","dmgbuild >=1.6.1","filelock >=3.12.3","packaging >=24.0","python >=3.10,<3.11.0a0","python >=3.10,<3.11.0a0 *_cpython","python_abi 3.10.* *_cp310","setuptools >=65.6.3","tomli >=2.0.1"],"license":"PSF-2.0","license_family":"PSF","md5":"c397844b75264ddff547441eb79ee97c","name":"cx_freeze","sha256":"3e8b8086b4bbb2b7dd929edce8b8bad46788ea64ce8e88a3ce283598a3a9b9ab","size":4111154,"subdir":"osx-64","timestamp":1744620708522,"version":"8.1.0.dev.1744484199"},"cx_freeze-8.1.0.dev.1744484199-py311hff4f217_0.conda":{"build":"py311hff4f217_0","build_number":0,"depends":["__osx >=10.13","dmgbuild >=1.6.1","filelock >=3.12.3","packaging >=24.0","python >=3.11,<3.12.0a0","python >=3.11,<3.12.0a0 *_cpython","python_abi 3.11.* *_cp311","setuptools >=65.6.3"],"license":"PSF-2.0","license_family":"PSF","md5":"b8c7b272e955bf4c319813ba595a69e6","name":"cx_freeze","sha256":"fbcf2ec105c4bcd98441ff1aa70a29d35f70a90290355fbf8d382e41c75cabce","size":4290875,"subdir":"osx-64","timestamp":1744620715229,"version":"8.1.0.dev.1744484199"},"cx_freeze-8.1.0.dev.1744484199-py312h323ca87_0.conda":{"build":"py312h323ca87_0","build_number":0,"depends":["__osx >=10.13","dmgbuild >=1.6.1","filelock >=3.12.3","packaging >=24.0","python >=3.12,<3.13.0a0","python >=3.12,<3.13.0a0 *_cpython","python_abi 3.12.* *_cp312","setuptools >=65.6.3"],"license":"PSF-2.0","license_family":"PSF","md5":"82d0300e7848f4f281ee99f4b46b0b23","name":"cx_freeze","sha256":"d35ce799203a10c4a9327621294fb1de66ea9684f7f054822ec426225739176e","size":4159788,"subdir":"osx-64","timestamp":1744620527647,"version":"8.1.0.dev.1744484199"},"cx_freeze-8.1.0.dev.1744484199-py313hb9c082b_0.conda":{"build":"py313hb9c082b_0","build_number":0,"depends":["__osx >=10.13","dmgbuild >=1.6.1","filelock >=3.12.3","packaging >=24.0","python >=3.13,<3.14.0a0","python >=3.13,<3.14.0a0 *_cp313","python_abi 3.13.* *_cp313","setuptools >=65.6.3"],"license":"PSF-2.0","license_family":"PSF","md5":"9572b88edb3376b3189948e5f2a35ed0","name":"cx_freeze","sha256":"d57ca8ef19774701db668a7723b216a17473a334db4a985028057726a74710a1","size":4149955,"subdir":"osx-64","timestamp":1744620872030,"version":"8.1.0.dev.1744484199"},"cx_freeze-8.1.0.dev.1744484199-py39h42342cc_0.conda":{"build":"py39h42342cc_0","build_number":0,"depends":["__osx >=10.13","dmgbuild >=1.6.1","filelock >=3.12.3","packaging >=24.0","python >=3.9,<3.10.0a0","python >=3.9,<3.10.0a0 *_cpython","python_abi 3.9.* *_cp39","setuptools >=65.6.3","tomli >=2.0.1","typing_extensions >=4.10.0"],"license":"PSF-2.0","license_family":"PSF","md5":"4908a48a45c3db1183b954ae5bde5bb6","name":"cx_freeze","sha256":"1bb3d63a232f0441c1dec569c6e3007a1403983ab51bed1a97fc08d182c22299","size":4051444,"subdir":"osx-64","timestamp":1744620542674,"version":"8.1.0.dev.1744484199"}},"removed":[],"repodata_version":1}