{"info":{"subdir":"linux-64"},"packages":{},"packages.conda":{"cx_freeze-8.4.0.dev.1747885327-py310ha75aee5_0.conda":{"build":"py310ha75aee5_0","build_number":0,"depends":["__glibc >=2.17,<3.0.a0","filelock >=3.12.3","libgcc >=13","packaging >=24.0","patchelf >=0.14","python >=3.10,<3.11.0a0","python_abi 3.10.* *_cp310","setuptools >=65.6.3","tomli >=2.0.1"],"legacy_bz2_md5":null,"license":"PSF-2.0","license_family":"PSF","md5":"ceaefd42a3e00a70d138ce6d0987fb03","name":"cx_freeze","sha256":"4d9414818a01894c02e7b4dc97de96a5acba913b6d8ac6c65bfbf99b87db492c","size":4128193,"subdir":"linux-64","timestamp":1747903715508,"version":"8.4.0.dev.1747885327"},"cx_freeze-8.4.0.dev.1747885327-py311h9ecbd09_0.conda":{"build":"py311h9ecbd09_0","build_number":0,"depends":["__glibc >=2.17,<3.0.a0","filelock >=3.12.3","libgcc >=13","packaging >=24.0","patchelf >=0.14","python >=3.11,<3.12.0a0","python_abi 3.11.* *_cp311","setuptools >=65.6.3"],"legacy_bz2_md5":null,"license":"PSF-2.0","license_family":"PSF","md5":"14d8b3440d8a7a3b94115e918485a95d","name":"cx_freeze","sha256":"f8a7928746c44d1b1399b09a6e42e40a036d4c7259614b8173fb2a96d4e8e2d7","size":4212511,"subdir":"linux-64","timestamp":1747903719626,"version":"8.4.0.dev.1747885327"},"cx_freeze-8.4.0.dev.1747885327-py312h66e93f0_0.conda":{"build":"py312h66e93f0_0","build_number":0,"depends":["__glibc >=2.17,<3.0.a0","filelock >=3.12.3","libgcc >=13","packaging >=24.0","patchelf >=0.14","python >=3.12,<3.13.0a0","python_abi 3.12.* *_cp312","setuptools >=65.6.3"],"legacy_bz2_md5":null,"license":"PSF-2.0","license_family":"PSF","md5":"c92f866f65c6bf1160aeb959b204176a","name":"cx_freeze","sha256":"a3a25648cb2e0a2a1ab366b96278d173fbc03f5197acf6095cc02fecd04c6549","size":4202450,"subdir":"linux-64","timestamp":1747903714666,"version":"8.4.0.dev.1747885327"},"cx_freeze-8.4.0.dev.1747885327-py313h536fd9c_0.conda":{"build":"py313h536fd9c_0","build_number":0,"depends":["__glibc >=2.17,<3.0.a0","filelock >=3.12.3","libgcc >=13","packaging >=24.0","patchelf >=0.14","python >=3.13,<3.14.0a0","python_abi 3.13.* *_cp313","setuptools >=65.6.3"],"legacy_bz2_md5":null,"license":"PSF-2.0","license_family":"PSF","md5":"ed445082354f7d2dbf3b7e1ed66264e3","name":"cx_freeze","sha256":"26e773761d50e1305f05c4fe2aa40c99b5c3eea214a21c2a27c249bfb7759dac","size":4203790,"subdir":"linux-64","timestamp":1747903718765,"version":"8.4.0.dev.1747885327"},"cx_freeze-8.4.0.dev.1747885327-py39h8cd3c5a_0.conda":{"build":"py39h8cd3c5a_0","build_number":0,"depends":["__glibc >=2.17,<3.0.a0","filelock >=3.12.3","libgcc >=13","packaging >=24.0","patchelf >=0.14","python >=3.9,<3.10.0a0","python_abi 3.9.* *_cp39","setuptools >=65.6.3","tomli >=2.0.1"],"legacy_bz2_md5":null,"license":"PSF-2.0","license_family":"PSF","md5":"af02585702760d61e52663fb58b062ed","name":"cx_freeze","sha256":"4263a0ce703299951223fa87ef255aa9b4a1a6dca50cd2ded548e2db18ef49c6","size":4119515,"subdir":"linux-64","timestamp":1747903713596,"version":"8.4.0.dev.1747885327"}},"removed":[],"repodata_version":1}